esbuild/__init__.py
esbuild/__main__.py
esbuild/exceptions.py
esbuild/installation.py
esbuild-0.1.2.dist-info/LICENSE
esbuild-0.1.2.dist-info/WHEEL
esbuild-0.1.2.dist-info/METADATA
esbuild-0.1.2.dist-info/RECORD
